setup.py
stardatetime/__init__.py
stardatetime/stardatetime.py
stardatetime.egg-info/PKG-INFO
stardatetime.egg-info/SOURCES.txt
stardatetime.egg-info/dependency_links.txt
stardatetime.egg-info/not-zip-safe
stardatetime.egg-info/top_level.txt