Metadata-Version: 1.0
Name: stardatetime
Version: 0.1.1
Summary: datetime for the next generation
Home-page: https://github.com/amygdalama/stardatetime
Author: Amy Hanlon
Author-email: UNKNOWN
License: MIT
Platform: UNKNOWN
